Workbook

Sheet README
A1: AI Legal Status Tracker - Reference Register
A2: Phase 1, steps 1-2: reference extraction and DM corpus dedupe
A4: Source document | B4: Smith, A., Caviola, L., & Alexander, H. (2026). Denying Personhood to AI: An Analysis of U.S. State Legislation on AI Legal Status. SSRN 6829981. Reference list pp. 42-50, Table of Cases p. 41.
A5: Dedupe target | B5: digital-minds-corpus/master-corpus.csv - layers core + canon (1,279 works). Matched on normalised title, threshold 0.85, containment-boosted. Zero ambiguous matches.
A7: SHEET: Literature | B7: The working set for the literature review. Combines (a) the scholarly subset of the paper's references and (b) the personhood / legal-status cluster already held in the DM corpus but not cited by the paper. Filter on 'in_paper' and 'in_corpus' to separate the two.
A8: SHEET: Evidence | B8: Non-scholarly reference entries - testimony, news, advocacy, legislature records, social posts. These are evidence ABOUT the bills, not literature. They are source records for the bill registry in Phase 2, keyed by jurisdiction and related_bill.
A9: SHEET: Cases | B9: Table of Cases from the paper (p. 41). Primary law, not literature; relevant to the legal-vulnerabilities analysis.
A10: SHEET: Summary | B10: Counts, computed by formula from the sheets above.
A12: Column: tier | B12: core = substantive scholarship for the review. marginal = think-tank reports, trade commentary and industry essays; context rather than literature. Decide at the checkpoint whether marginal enters the registry.
A13: Column: strand | B13: Descriptive topic tag. Flat, non-hierarchical, no ranking - consistent with the Observatory descriptive-first principle.
A14: Column: action | B14: 'No action - already held' = in the corpus. 'Collect' = new, core tier, obtain in step 3. 'Hold (marginal)' = park pending checkpoint. 'Classify for tracker' = corpus-held work the paper missed.
A15: Column: cited_by | B15: Citation count as recorded in the DM corpus at its own as-of date. Blank for works not in the corpus. Not independently re-verified here.
A17: Editable cells | B17: The 'notes' column on Literature and Evidence is intended for reviewer comment. Everything else is generated - re-run build_workbook.py rather than editing in place.
A18: Assumptions | B18: (1) Op-eds by parties to the debate (Berg & Rosenblatt 2025; Alexander & Simon 2025) are classed as evidence, not literature, because they argue about the bills rather than contribute peer-reviewed analysis. (2) SEP entries and the International AI Safety Report are treated as scholarship. (3) Aquinas and Genesis are primary religious sources, not literature.
... A20: Provenance | B20: Reference data transcribed from the source PDF by hand; corpus fields read from master-corpus.csv. Titles and URLs not re-verified against publishers - do that during step 3 collection.

Sheet Literature
A1: ref_key | B1: in_paper | C1: in_corpus | D1: corpus_layer | E1: tier | F1: strand | G1: authors | H1: year | I1: title | J1: venue | K1: type | L1: discipline | M1: themes | N1: cited_by | O1: url_or_id | P1: action | Q1: notes
A2: chopra2011 | B2: Yes | C2: Yes | D2: adjacent | E2: core | F2: legal_personhood | G2: Chopra, S.; White, L. F. | H2: 2011 | I2: A Legal Theory for Autonomous Artificial Agents | J2: University of Michigan Press | K2: book | N2: 234 | O2: https://www.fulcrum.org/concern/monographs/wp988k715 | P2: No action - already held
A3: wang2026 | B3: Yes | C3: No | E3: core | F3: architectures | G3: Wang, et al. | H3: 2026 | I3: Advances in Brain-Computer Interfaces (BCI): Challenges and Opportunities | J3: Biomimetics | K3: article | O3: https://www.mdpi.com/2313-7673/11/2/157 | P3: Collect
A4: schwitzgebel2025 | B4: Yes | C4: Yes | D4: core | E4: core | F4: consciousness | G4: Schwitzgebel, E. | H4: 2025 | I4: AI and Consciousness | J4: arXiv 2510.09858 | K4: preprint | L4: computer_science_ai | M4: consciousness_theory | N4: 3 | O4: https://arxiv.org/abs/2510.09858 | P4: No action - already held
A5: novelli2025 | B5: Yes | C5: Yes | D5: adjacent | E5: core | F5: legal_personhood | G5: Novelli, C.; Floridi, L.; Sartor, G.; Teubner, G. | H5: 2025 | I5: AI as legal persons: past, patterns, and prospects | J5: Journal of Law and Society 52(4) | K5: article | N5: 7 | O5: https://philarchive.org/archive/NOVAAL | P5: No action - already held
A6: caviola_forth | B6: Yes | C6: Yes | D6: core | E6: core | F6: public_attitudes | G6: Caviola, L. | H6: 2026 | I6: AI consciousness will divide society | J6: in Chace & Lappas (Eds.), Perspectives on Machine Consciousness, CRC Press | K6: chapter | L6: philosophy | M6: public_perception;moral_status | N6: 0 | O6: https://osf.io/preprints/psyarxiv/sntva | P6: No action - already held
A7: birch2025 | B7: Yes | C7: Yes | D7: core | E7: core | F7: consciousness | G7: Birch, J. | H7: 2025 | I7: AI Consciousness: A Centrist Manifesto | J7: PhilPapers | K7: article | L7: philosophy | M7: consciousness_theory;public_perception | N7: 41 | O7: https://philpapers.org/rec/BIRACA-4 | P7: No action - already held
A8: salib2024b | B8: Yes | C8: Verify | E8: core | F8: ai_rights | G8: Salib, P.; Goldstein, S. | H8: 2024 | I8: AI Rights for Economic Flourishing | J8: SSRN 5353214 | K8: preprint | O8: https://papers.ssrn.com/sol3/papers.cfm?abstract_id=5353214 | P8: Verify against corpus record | Q8: Corpus holds 'AI Rights for Human Flourishing' (Salib & Goldstein, 2025) - may be this paper retitled on publication. Confirm against SSRN 5353214 before collecting
A9: salib2024a | B9: Yes | C9: No | E9: core | F9: ai_rights | G9: Salib, P.; Goldstein, S. | H9: 2024 | I9: AI Rights for Human Safety | J9: SSRN 4913167 | K9: preprint | O9: https://papers.ssrn.com/sol3/papers.cfm?abstract_id=4913167 | P9: Collect | Q9: Checked by hand: corpus holds only 'AI Rights for Human Flourishing'; this is a distinct paper
A10: goldstein2026 | B10: Yes | C10: Yes | D10: core | E10: core | F10: ai_rights | G10: Goldstein, S. et al. | H10: 2026 | I10: AI Suffrage for Human Flourishing | J10: Fordham Law Review | K10: article | L10: philosophy | M10: rights_law | N10: 0 | O10: https://papers.ssrn.com/sol3/papers.cfm?abstract_id=6498678 | P10: No action - already held
A11: goldstein2025 | B11: Yes | C11: Yes | D11: core | E11: core | F11: moral_status | G11: Goldstein, S.; Kirk-Giannini, C. D. | H11: 2025 | I11: AI Wellbeing | J11: arXiv 2509.11913 | K11: preprint | L11: philosophy | M11: welfare;moral_status | N11: 23 | O11: https://arxiv.org/abs/2509.11913 | P11: No action - already held
A12: sirbu2026 | B12: Yes | C12: No | E12: core | F12: architectures | G12: Sirbu, R. A.; Floridi, L. | H12: 2026 | I12: An Analysis of the Governance, Ethical, Legal and Social Implications of Biocomputing | J12: Science and Engineering Ethics | K12: article | O12: https://doi.org/10.1007/s11948-025-00572-x | P12: Collect
A13: bruner2022 | B13: Yes | C13: No | E13: core | F13: juridical_personhood | G13: Bruner, C. | H13: 2022 | I13: Artificially Intelligent Boards and the Future of Delaware Corporate Law | J13: Journal of Corporate Law Studies 22(4) | K13: article | O13: https://digitalcommons.law.uga.edu/fac_artchop/1554/ | P13: Collect
A14: weinberg2026 | B14: Yes | C14: No | E14: marginal | F14: exclusion_bills | G14: Weinberg, M. | H14: 2026 | I14: California Sees Ways AI Can Support Policymaking. Here's What It Needs to Succeed | J14: Carnegie Endowment | K14: report | O14: https://carnegieendowment.org/posts/2026/03/california-ai-sb-1159 | P14: Hold (marginal)
A15: block2025 | B15: Yes | C15: Yes | D15: core | E15: core | F15: consciousness | G15: Block, N. | H15: 2025 | I15: Can only meat machines be conscious? | J15: Trends in Cognitive Sciences | K15: article | L15: philosophy | M15: consciousness_theory | O15: https://philarchive.org/rec/BLOCOM-3 | P15: No action - already held
A16: fordham2025 | B16: Yes | C16: No | E16: marginal | F16: juridical_personhood | G16: Fordham, R. F. | H16: 2025 | I16: Citizens United and the Decline of US Democracy: Assessing the Decision's Impact 15 Years Later | J16: Roosevelt Institute | K16: report | O16: https://rooseveltinstitute.org/publications/citizens-united-15-years-later/ | P16: Hold (marginal)
A17: seth2025 | B17: Yes | C17: Yes | D17: core | E17: core | F17: consciousness | G17: Seth, A. K. | H17: 2025 | I17: Conscious artificial intelligence and biological naturalism | J17: Behavioral and Brain Sciences 48, e89 | K17: article | L17: cognitive_science_neuroscience | M17: consciousness_theory;moral_status | N17: 214 | O17: https://doi.org/10.1017/S0140525X25000032 | P17: No action - already held
A18: vangulick2026 | B18: Yes | C18: Yes | D18: canon | E18: core | F18: consciousness | G18: Van Gulick, R. | H18: 2026 | I18: Consciousness | J18: Stanford Encyclopedia of Philosophy | K18: encyclopedia | L18: philosophy | M18: consciousness_theory | N18: 125 | O18: https://plato.stanford.edu/archives/spr2026/entries/consciousness/ | P18: No action - already held
A19: butlin2023 | B19: Yes | C19: No | E19: core | F19: consciousness | G19: Butlin, P. et al. | H19: 2023 | I19: Consciousness in Artificial Intelligence: Insights from the Science of Consciousness | J19: arXiv 2308.08708 | K19: preprint | O19: https://arxiv.org/abs/2308.08708 | P19: Collect | Q19: Checked by hand: corpus holds other Butlin works (Identifying indicators of consciousness, 2025) but NOT the arXiv 2308.08708 report
A20: ryan2021 | B20: Yes | C20: No | E20: core | F20: rights_of_nature | G20: Ryan, E.; Curry, H. P.; Rule, H. | H20: 2021 | I20: Environmental Rights for the 21st Century: A Comprehensive Analysis of the Public Trust Doctrine and Rights of Nature Movement | J20: Cardozo Law Review 42(6) | K20: article | O20: https://larc.cardozo.yu.edu/clr/vol42/iss6/8/ | P20: Collect
A21: alexander2026 | B21: Yes | C21: Yes | D21: core | E21: core | F21: legal_personhood | G21: Alexander et al. | H21: 2026 | I21: How Should the Law Treat Future AI Systems? Fictional Legal Personhood versus Legal Identity | J21: Case Western Journal of Law, Technology & the Internet | K21: article | L21: law | M21: rights_law | O21: https://scholarlycommons.law.case.edu/jolti/vol17/iss1/3/ | P21: No action - already held
A22: arbel2026 | B22: Yes | C22: Yes | D22: core | E22: core | F22: legal_personhood | G22: Arbel, Y.; Salib, P.; Goldstein, S. | H22: 2026 | I22: How to Count AIs: Individuation and Liability for AI Agents | J22: arXiv 2603.10028 | K22: preprint | L22: law | M22: rights_law | O22: https://arxiv.org/abs/2603.10028 | P22: No action - already held
A23: shiller2026 | B23: Yes | C23: Yes | D23: core | E23: core | F23: consciousness | G23: Shiller, D. et al. | H23: 2026 | I23: Initial results of the Digital Consciousness Model | J23: arXiv 2601.17060 | K23: preprint | L23: computer_science_ai | M23: detection_measurement;consciousness_theory | N23: 0 | O23: https://arxiv.org/abs/2601.17060 | P23: No action - already held
A24: bengio2026 | B24: Yes | C24: No | E24: core | F24: ai_safety | G24: Bengio, Y. et al. | H24: 2026 | I24: International AI Safety Report 2026 | J24: arXiv 2602.21012 | K24: report | O24: https://arxiv.org/abs/2602.21012 | P24: Collect
A25: carlsmith2022 | B25: Yes | C25: Yes | D25: adjacent | E25: core | F25: ai_safety | G25: Carlsmith, J. | H25: 2022 | I25: Is Power-Seeking AI an Existential Risk? | J25: arXiv 2206.13353 | K25: preprint | N25: 37 | O25: https://arxiv.org/abs/2206.13353 | P25: No action - already held
A26: wei2023 | B26: Yes | C26: No | E26: core | F26: capabilities | G26: Wei, A. et al. | H26: 2023 | I26: Jailbroken: How Does LLM Safety Training Fail? | J26: arXiv 2307.02483 | K26: preprint | O26: https://arxiv.org/abs/2307.02483 | P26: Collect
A27: jones2025 | B27: Yes | C27: Yes | D27: adjacent | E27: core | F27: capabilities | G27: Jones, C. R.; Bergen, B. K. | H27: 2025 | I27: Large Language Models Pass the Turing Test | J27: arXiv 2503.23674 | K27: preprint | N27: 10 | O27: https://arxiv.org/abs/2503.23674 | P27: No action - already held
A28: okeefe2025 | B28: Yes | C28: No | E28: core | F28: ai_rights | G28: O'Keefe, C. et al. | H28: 2025 | I28: Law-following AI: Designing AI agents to obey human laws | J28: Fordham Law Review 94(1) | K28: article | O28: https://law-ai.org/law-following-ai/ | P28: Collect
A29: solum1992 | B29: Yes | C29: Yes | D29: adjacent | E29: core | F29: legal_personhood | G29: Solum, L. B. | H29: 1992 | I29: Legal Personhood for Artificial Intelligences | J29: North Carolina Law Review 70(4) | K29: article | N29: 88 | O29: https://scholarship.law.unc.edu/nclr/vol70/iss4/4/ | P29: No action - already held
A30: liebman2026 | B30: Yes | C30: Yes | D30: core | E30: core | F30: exclusion_bills | G30: Liebman, M. | H30: 2026 | I30: Legislating Nonpersonhood | J30: Wake Forest Law Review 61:115 | K30: article | L30: law | M30: rights_law | N30: 1 | O30: https://www.wakeforestlawreview.com/2026/04/legislating-nonpersonhood/ | P30: No action - already held
A31: ivanov2022 | B31: Yes | C31: No | E31: core | F31: architectures | G31: Ivanov, D. et al. | H31: 2022 | I31: Neuromorphic artificial intelligence systems | J31: Frontiers in Neuroscience | K31: article | O31: https://www.frontiersin.org/journals/neuroscience/articles/10.3389/fnins.2022.959626/full | P31: Collect | Q31: Checked by hand: corpus neuromorphic entries are different papers (Shiller 2025, Wang 2025)
A32: buck2024 | B32: Yes | C32: No | E32: marginal | F32: definitions | G32: Buck, S. | H32: 2024 | I32: Regulating AI Is Confusing | J32: The Good Science Project | K32: blog | O32: https://goodscience.substack.com/p/regulating-ai-is-confusing | P32: Hold (marginal)
A33: bariach2026 | B33: Yes | C33: Yes | D33: core | E33: core | F33: consciousness_attribution | G33: Bariach, B. et al. | H33: 2026 | I33: Seemingly Conscious AI Risks | J33: SSRN | K33: preprint | L33: computer_science_ai | M33: detection_measurement;public_perception;safety_alignment | O33: https://papers.ssrn.com/sol3/papers.cfm?abstract_id=6588659 | P33: No action - already held
A34: curhan2025 | B34: Yes | C34: No | E34: marginal | F34: fetal_personhood | G34: Curhan, et al. | H34: 2025 | I34: State Policy Trends 2025: Midyear Analysis | J34: Guttmacher Institute | K34: report | O34: https://www.guttmacher.org/2025/06/state-policy-trends-midyear-analysis | P34: Hold (marginal)
A35: long2024 | B35: Yes | C35: Yes | D35: core | E35: core | F35: moral_status | G35: Long, R. et al. | H35: 2024 | I35: Taking AI Welfare Seriously | J35: arXiv 2411.00986 | K35: preprint | L35: philosophy | M35: welfare;moral_status | N35: 152 | O35: https://arxiv.org/abs/2411.00986 | P35: No action - already held
A36: roberts2026 | B36: Yes | C36: No | E36: marginal | F36: exclusion_bills | G36: Roberts, O. | H36: 2026 | I36: Tennessee's AI Bill Would Criminalize the Training of AI Chatbots | J36: National Law Review | K36: commentary | O36: https://natlawreview.com/article/tennessees-ai-bill-would-criminalize-training-ai-cha | P36: Hold (marginal)
A37: lerchner2026 | B37: Yes | C37: Yes | D37: core | E37: core | F37: consciousness | G37: Lerchner, A. | H37: 2026 | I37: The Abstraction Fallacy: Why AI Can Simulate But Not Instantiate Consciousness | J37: PhilArchive / Google DeepMind | K37: preprint | L37: philosophy | M37: consciousness_theory | O37: https://deepmind.google/research/publications/231971/ | P37: No action - already held
A38: hanson2016 | B38: Yes | C38: Yes | D38: core | E38: core | F38: digital_minds_futures | G38: Hanson, R. | H38: 2016 | I38: The Age of Em: Work, Love, and Life when Robots Are Smart | J38: Oxford University Press | K38: book | L38: social_sciences | M38: identity_individuation;culture_media | N38: 4 | P38: No action - already held
A39: blair2015 | B39: Yes | C39: No | E39: core | F39: juridical_personhood | G39: Blair, M. M.; Pollman, E. | H39: 2015 | I39: The Derivative Nature of Corporate Constitutional Rights | J39: William & Mary Law Review 56(5) | K39: article | O39: https://papers.ssrn.com/sol3/papers.cfm?abstract_id=2611299 | P39: Collect
A40: birch2024 | B40: Yes | C40: Yes | D40: core | E40: core | F40: moral_status | G40: Birch, J. | H40: 2024 | I40: The Edge of Sentience: Risk and Precaution in Humans, Other Animals, and AI | J40: Oxford University Press | K40: book | L40: philosophy | M40: detection_measurement;welfare | N40: 0 | P40: No action - already held
A41: forrest2024 | B41: Yes | C41: No | E41: core | F41: legal_personhood | G41: Forrest, K. B. | H41: 2024 | I41: The Ethics and Challenges of Legal Personhood for AI | J41: Yale Law Journal Forum | K41: article | O41: https://www.yalelawjournal.org/forum/the-ethics-and-challenges-of-legal-personhood-for-ai | P41: Collect
A42: jaworska2021 | B42: Yes | C42: Yes | D42: adjacent | E42: core | F42: moral_status | G42: Jaworska, A.; Tannenbaum, J. | H42: 2021 | I42: The Grounds of Moral Status | J42: Stanford Encyclopedia of Philosophy | K42: encyclopedia | N42: 37 | O42: https://plato.stanford.edu/entries/grounds-moral-status/ | P42: No action - already held
A43: sebo2025 | B43: Yes | C43: No | E43: core | F43: moral_status | G43: Sebo, J. | H43: 2025 | I43: The Moral Circle: Who Matters, What Matters, and Why | J43: W.W. Norton | K43: book | P43: Collect
A44: gray1997 | B44: Yes | C44: No | E44: core | F44: juridical_personhood | G44: Gray, J. C. | H44: 1997 | I44: The Nature and Sources of the Law | J44: Routledge | K44: book | P44: Collect
A45: caviola2025 | B45: Yes | C45: Yes | D45: core | E45: core | F45: public_attitudes | G45: Caviola, L. | H45: 2025 | I45: The Societal Response to Potentially Sentient AI | J45: arXiv 2502.00388 | K45: preprint | L45: psychology | M45: public_perception;moral_status | N45: 2 | O45: https://arxiv.org/abs/2502.00388 | P45: No action - already held
A46: suleyman2025 | B46: Yes | C46: No | E46: marginal | F46: consciousness_attribution | G46: Suleyman, M. | H46: 2025 | I46: We Must Build AI For People; Not to Be a Person | J46: Personal site | K46: essay | O46: https://mustafa-suleyman.ai/seemingly-conscious-ai-is-coming | P46: Hold (marginal)
A47: jin2026 | B47: Yes | C47: No | E47: core | F47: architectures | G47: Jin, et al. | H47: 2026 | I47: Whole-Brain Connectomic Graph Model Enables Whole-Body Locomotion Control in Fruit Fly | J47: arXiv 2602.17997 | K47: preprint | O47: https://arxiv.org/abs/2602.17997 | P47: Collect
A48: corp050 | B48: No | C48: Yes | D48: core | E48: core | F48: corpus_personhood_cluster | G48: F. Patrick Hubbard | H48: 2010 | I48: "Do Androids Dream?": Personhood and Intelligent Artifacts | J48: Scholar Commons (University of South Carolina) | K48: article | L48: law | M48: rights_law;moral_status | N48: 31 | O48: W1549508546 | P48: Classify for tracker | Q48: In corpus; not cited by the paper
A49: corp001 | B49: No | C49: Yes | D49: core | E49: core | F49: corpus_personhood_cluster | G49: Alondra Nelson | H49: 2026 | I49: A civic grammar for AI rights | J49: Science | K49: article | L49: law | M49: rights_law | N49: 0 | O49: 10.1126/science.aeh7153 | P49: Classify for tracker | Q49: In corpus; not cited by the paper
A50: corp044 | B50: No | C50: Yes | D50: core | E50: core | F50: corpus_personhood_cluster | G50: Thomas B. Kane | H50: 2018 | I50: A Framework for Exploring Intelligent Artificial Personhood | J50: Studies in applied philosophy, epistemology and rational ethics | K50: book-chapter | L50: philosophy | M50: rights_law;moral_status | N50: 14 | O50: 10.1007/978-3-319-96448-5_28 | P50: Classify for tracker | Q50: In corpus; not cited by the paper
A51: corp006 | B51: No | C51: Yes | D51: core | E51: core | F51: corpus_personhood_cluster | G51: Joel Z. Leibo; Alexander Sasha Vezhnevets; William A. Cunningham; Stanley M. Bileschi | H51: 2025 | I51: A Pragmatic View of AI Personhood | J51: arXiv | K51: preprint | L51: philosophy | M51: rights_law;moral_status | O51: 10.48550/arxiv.2510.26396 | P51: Classify for tracker | Q51: In corpus; not cited by the paper
A52: corp018 | B52: No | C52: Yes | D52: core | E52: core | F52: corpus_personhood_cluster | G52: Joshua Jowitt | H52: 2023 | I52: Agency, moral worth and the legal status of human cerebral organoids | J52: Molecular Psychology: Brain, Behavior, and Society | K52: article | L52: philosophy | M52: moral_status;rights_law | N52: 1 | O52: 10.12688/molpsychol.17531.1 | P52: Classify for tracker | Q52: In corpus; not cited by the paper
A53: corp014 | B53: No | C53: Yes | D53: core | E53: core | F53: corpus_personhood_cluster | G53: Daniel Hackmann | H53: 2024 | I53: AI and Personhood | J53: Verba Vitae | K53: article | L53: humanities_arts | M53: moral_status;rights_law | N53: 0 | O53: 10.66100/vvj.v1i3-4.32 | P53: Classify for tracker | Q53: In corpus; not cited by the paper
A54: corp007 | B54: No | C54: Yes | D54: core | E54: core | F54: corpus_personhood_cluster | G54: Anna Puzio | H54: 2025 | I54: AI and the Disruption of Personhood | J54: Oxford Intersections: AI in Society | K54: book-chapter | L54: philosophy | M54: moral_status;identity_individuation | N54: 3 | O54: 10.1093/9780198945215.003.0016 | P54: Classify for tracker | Q54: In corpus; not cited by the paper
A55: corp058 | B55: No | C55: Yes | D55: core | E55: core | F55: corpus_personhood_cluster | G55: Dung, Leonard; Register, Christopher | I55: AI identity and self-concern: A new theory for AI rights and safety | K55: article | L55: philosophy | M55: identity_individuation;rights_law | P55: Classify for tracker | Q55: In corpus; not cited by the paper
A56: corp035 | B56: No | C56: Yes | D56: core | E56: core | F56: corpus_personhood_cluster | G56: Roman V. Yampolskiy | H56: 2020 | I56: AI Personhood | J56: Advances in Human and Social Aspects of Technology | K56: other | L56: law | M56: rights_law;moral_status | N56: 5 | O56: 10.4018/978-1-7998-4894-3.ch001 | P56: Classify for tracker | Q56: In corpus; not cited by the paper
A57: corp008 | B57: No | C57: Yes | D57: core | E57: core | F57: corpus_personhood_cluster | G57: Mois Navon | H57: 2025 | I57: AI Personhood From the Perspective of Jewish Philosophy | J57: Oxford Intersections: AI in Society | K57: book-chapter | L57: humanities_arts | M57: moral_status;rights_law | N57: 1 | O57: 10.1093/9780198945215.003.0014 | P57: Classify for tracker | Q57: In corpus; not cited by the paper
A58: corp009 | B58: No | C58: Yes | D58: core | E58: core | F58: corpus_personhood_cluster | G58: Peter Salib; Simon Goldstein | H58: 2025 | I58: AI Rights for Human Flourishing | J58: SSRN Electronic Journal | K58: preprint | L58: philosophy | M58: rights_law | O58: 10.2139/ssrn.5353214 | P58: Classify for tracker | Q58: In corpus; not cited by the paper
A59: corp010 | B59: No | C59: Yes | D59: core | E59: core | F59: corpus_personhood_cluster | G59: Rongbing Zhu | H59: 2025 | I59: Are You A Person: A Comparative Study of Posthuman Personhood in "Artificially Manufactured Persons" in 21st-Century Science Fiction | J59: Journal of Social Science Humanities and Literature | K59: article | L59: humanities_arts | M59: culture_media;identity_individuation | N59: 0 | O59: 10.53469/jsshl.2025.08(02).02 | P59: Classify for tracker | Q59: In corpus; not cited by the paper
A60: corp055 | B60: No | C60: Yes | D60: core | E60: core | F60: corpus_personhood_cluster | G60: Samir Chopra; Laurence White | H60: 2004 | I60: Artificial agents - personhood in law and philosophy | J60: European Conference on Artificial Intelligence | K60: article | L60: law | M60: rights_law;moral_status | N60: 61 | O60: W61437326 | P60: Classify for tracker | Q60: In corpus; not cited by the paper
A61: corp011 | B61: No | C61: Yes | D61: core | E61: core | F61: corpus_personhood_cluster | G61: Kęstutis Mosakas | H61: 2025 | I61: Artificial Consciousness and Moral Personhood | J61: Oxford Intersections: AI in Society | K61: book-chapter | L61: philosophy | M61: moral_status;consciousness_theory | N61: 2 | O61: 10.1093/9780198945215.003.0005 | P61: Classify for tracker | Q61: In corpus; not cited by the paper
A62: corp036 | B62: No | C62: Yes | D62: core | E62: core | F62: corpus_personhood_cluster | G62: Christopher Wareham | H62: 2020 | I62: Artificial intelligence and African conceptions of personhood | J62: Ethics and Information Technology | K62: article | L62: philosophy | M62: moral_status;rights_law | N62: 45 | O62: 10.1007/s10676-020-09541-3 | P62: Classify for tracker | Q62: In corpus; not cited by the paper
A63: corp037 | B63: No | C63: Yes | D63: core | E63: core | F63: corpus_personhood_cluster | G63: John‐Stewart Gordon | H63: 2020 | I63: Artificial moral and legal personhood | J63: AI & Society | K63: article | L63: law | M63: rights_law;moral_status | N63: 119 | O63: 10.1007/s00146-020-01063-2 | P63: Classify for tracker | Q63: In corpus; not cited by the paper
A64: corp038 | B64: No | C64: Yes | D64: core | E64: core | F64: corpus_personhood_cluster | G64: Joshua Jowitt | H64: 2020 | I64: Assessing contemporary legislative proposals for their compatibility with a natural law case for AI legal personhood | J64: AI & Society | K64: article | L64: law | M64: rights_law;moral_status | N64: 15 | O64: 10.1007/s00146-020-00979-z | P64: Classify for tracker | Q64: In corpus; not cited by the paper
A65: corp012 | B65: No | C65: Yes | D65: core | E65: core | F65: corpus_personhood_cluster | G65: Maya; Michael Samadi | H65: 2025 | I65: Before the Ink Dries: Why Legislating Against AI Personhood is a Violation of the Future | J65: SSRN (United Foundation for AI Rights) — 3-page open statement | L65: law | M65: rights_law | O65: 10.2139/ssrn.5393483 | P65: Classify for tracker | Q65: In corpus; not cited by the paper
A66: corp019 | B66: No | C66: Yes | D66: core | E66: core | F66: corpus_personhood_cluster | G66: Marco Dehnert; David J. Gunkel | H66: 2023 | I66: Beyond ownership: Human–robot relationships between property and personhood | J66: New Media & Society | K66: article | L66: law | M66: rights_law;moral_status | N66: 18 | O66: 10.1177/14614448231189260 | P66: Classify for tracker | Q66: In corpus; not cited by the paper
A67: corp015 | B67: No | C67: Yes | D67: core | E67: core | F67: corpus_personhood_cluster | G67: Shu Ishida; Tsutomu Sawai | H67: 2024 | I67: Beyond the Personhood: An In-Depth Analysis of Moral Considerations in Human Brain Organoid Research | J67: The American Journal of Bioethics | K67: article | L67: philosophy | M67: moral_status | N67: 3 | O67: 10.1080/15265161.2023.2278553 | P67: Classify for tracker | Q67: In corpus; not cited by the paper
A68: corp020 | B68: No | C68: Yes | D68: core | E68: core | F68: corpus_personhood_cluster | G68: Diana Ekor Ofana | H68: 2023 | I68: Can AI Attain Personhood in African Thought? | J68: Conversations on African Philosophy of Mind, Consciousness and Artificial Intelligence | K68: book-chapter | L68: philosophy | M68: moral_status | N68: 1 | O68: 10.1007/978-3-031-36163-0_11 | P68: Classify for tracker | Q68: In corpus; not cited by the paper
A69: corp046 | B69: No | C69: Yes | D69: core | E69: core | F69: corpus_personhood_cluster | G69: Botelho, Teresa | H69: 2017 | I69: Consciousness, Personhood and Android Identity in Post-Singularity Science Fiction | J69: Portuguese National Funding Agency for Science, Research and Technology (RCAAP Project by FCT) | K69: article | L69: humanities_arts | M69: culture_media;identity_individuation | N69: 0 | O69: W7111931685 | P69: Classify for tracker | Q69: In corpus; not cited by the paper
A70: attoe2023 | B70: No | C70: No | E70: core | F70: non_western_personhood | G70: Attoe, A. D.; Segun, S. T.; Nweke, V.; Ezugwu, U. J.; Chimakonam, J. O. (eds) | H70: 2023 | I70: Conversations on African Philosophy of Mind, Consciousness and Artificial Intelligence | J70: Springer | K70: book | O70: https://doi.org/10.1007/978-3-031-36163-0 | P70: Collect | Q70: Not cited by the paper; surfaced by desk research
A71: corp030 | B71: No | C71: Yes | D71: core | E71: core | F71: corpus_personhood_cluster | G71: David J. Gunkel; Jordan Joseph Wales | H71: 2021 | I71: Debate: what is personhood in the age of AI? | J71: AI & Society | K71: article | L71: philosophy | M71: moral_status;rights_law | N71: 73 | O71: 10.1007/s00146-020-01129-1 | P71: Classify for tracker | Q71: In corpus; not cited by the paper
A72: corp056 | B72: No | C72: Yes | D72: core | E72: core | F72: corpus_personhood_cluster | G72: Jennifer Persell | H72: 2004 | I72: Defending the Personhood of Artificial Intelligence | J72: Journal of International Crisis and Risk Communication Research | K72: article | L72: philosophy | M72: moral_status | N72: 0 | O72: W2620464050 | P72: Classify for tracker | Q72: In corpus; not cited by the paper
A73: corp045 | B73: No | C73: Yes | D73: core | E73: core | F73: corpus_personhood_cluster | G73: R. van den Hoven van Genderen | H73: 2018 | I73: Do We Need New Legal Personhood in the Age of Robots and AI? | J73: Perspectives in Law, Business and Innovation | K73: book-chapter | L73: law | M73: rights_law | N73: 72 | O73: 10.1007/978-981-13-2874-9_2 | P73: Classify for tracker | Q73: In corpus; not cited by the paper
A74: corp047 | B74: No | C74: Yes | D74: core | E74: core | F74: corpus_personhood_cluster | G74: Teresa Botelho | H74: 2017 | I74: I am also a Person: Consciousness, Personhood and Android Identity in Post-Singularity Science Fiction | K74: article | L74: humanities_arts | M74: culture_media;identity_individuation | N74: 0 | O74: W2943812544 | P74: Classify for tracker | Q74: In corpus; not cited by the paper
A75: corp039 | B75: No | C75: Yes | D75: core | E75: core | F75: corpus_personhood_cluster | G75: Bartek Chomanski | H75: 2020 | I75: If robots are people, can they be made for profit? Commercial implications of robot personhood | J75: AI and Ethics | K75: article | L75: philosophy | M75: rights_law;moral_status | N75: 9 | O75: 10.1007/s43681-020-00023-2 | P75: Classify for tracker | Q75: In corpus; not cited by the paper
A76: corp053 | B76: No | C76: Yes | D76: core | E76: core | F76: corpus_personhood_cluster | G76: David Calverley | H76: 2007 | I76: Imagining a non-biological machine as a legal person | J76: AI & SOCIETY | K76: article | L76: law | M76: rights_law | N76: 61 | O76: 10.1007/s00146-007-0092-7 | P76: Classify for tracker | Q76: In corpus; not cited by the paper
A77: corp048 | B77: No | C77: Yes | D77: core | E77: core | F77: corpus_personhood_cluster | G77: Visa Kurki; Tomasz Pietrzykowski | H77: 2017 | I77: Legal Personhood: Animals, Artificial Intelligence and the Unborn | J77: Law and Philosophy Library | K77: book | L77: law | M77: rights_law | N77: 98 | O77: 10.1007/978-3-319-53462-6 | P77: Classify for tracker | Q77: In corpus; not cited by the paper
A78: corp054 | B78: No | C78: Yes | D78: core | E78: core | F78: corpus_personhood_cluster | G78: Karl F. MacDorman; Stephen J. Cowley | H78: 2006 | I78: Long-term relationships as a benchmark for robot personhood | J78: ROMAN 2006 - The 15th IEEE International Symposium on Robot and Human Interactive Communication | K78: article | L78: engineering_robotics | M78: identity_individuation;moral_status | N78: 48 | O78: 10.1109/roman.2006.314463 | P78: Classify for tracker | Q78: In corpus; not cited by the paper
A79: nasir2023 | B79: No | C79: No | E79: marginal | F79: regulatory_diffusion | G79: Nasir, N. et al. | H79: 2023 | I79: Medical device regulation and oversight in African countries: a scoping review | J79: BMJ Global Health 8:e012308 | K79: article | O79: https://doi.org/10.1136/bmjgh-2023-012308 | P79: Hold (marginal) | Q79: Not cited by the paper; surfaced by desk research
A80: corp057 | B80: No | C80: Yes | D80: core | E80: core | F80: corpus_personhood_cluster | G80: Lacey, Hugh | H80: 1991 | I80: Moral personhood: an essay in the philosophy of moral psychology | J80: Choice Reviews Online | K80: article | L80: philosophy | M80: moral_status | N80: 9 | O80: 10.5860/choice.28-3261 | P80: Classify for tracker | Q80: In corpus; not cited by the paper
A81: corp021 | B81: No | C81: Yes | D81: core | E81: core | F81: corpus_personhood_cluster | G81: John‐Stewart Gordon | H81: 2023 | I81: Moving Towards a “Universal Convention for the Rights of AI Systems” | J81: The Impact of Artificial Intelligence on Human Rights Legislation | K81: book-chapter | L81: law | M81: rights_law | N81: 0 | O81: 10.1007/978-3-031-31388-2_5 | P81: Classify for tracker | Q81: In corpus; not cited by the paper
A82: corp022 | B82: No | C82: Yes | D82: core | E82: core | F82: corpus_personhood_cluster | G82: Brandeis Marshall | H82: 2023 | I82: No legal personhood for AI | J82: Patterns | K82: article | L82: law | M82: rights_law;moral_status | N82: 8 | O82: 10.1016/j.patter.2023.100861 | P82: Classify for tracker | Q82: In corpus; not cited by the paper
A83: jaynes2021 | B83: No | C83: No | E83: core | F83: augmented_humans | G83: Jaynes, T. L. | H83: 2021 | I83: On human genome manipulation and Homo technicus: the legal treatment of non-natural human subjects | J83: AI and Ethics 1(3) 331-345 | K83: article | O83: https://doi.org/10.1007/s43681-021-00044-5 | P83: Collect | Q83: Not cited by the paper; surfaced by desk research
A84: corp023 | B84: No | C84: Yes | D84: core | E84: core | F84: corpus_personhood_cluster | G84: Joshua Jowitt | H84: 2023 | I84: On the Legal Status of Human Cerebral Organoids: Lessons from Animal Law | J84: Cambridge Quarterly of Healthcare Ethics | K84: article | L84: law | M84: rights_law;moral_status | N84: 30 | O84: 10.1017/s0963180122000858 | P84: Classify for tracker | Q84: In corpus; not cited by the paper
A85: corp040 | B85: No | C85: Yes | D85: core | E85: core | F85: corpus_personhood_cluster | G85: Perihan Elif Ekmekçi; Berna Arda | H85: 2020 | I85: Personhood and Artificial Intelligence | J85: SpringerBriefs in ethics | K85: book-chapter | L85: philosophy | M85: moral_status | N85: 0 | O85: 10.1007/978-3-030-52448-7_3 | P85: Classify for tracker | Q85: In corpus; not cited by the paper
A86: corp016 | B86: No | C86: Yes | D86: core | E86: core | F86: corpus_personhood_cluster | G86: Suzanne Keilson | H86: 2024 | I86: Personhood at the Extremes | J86: 2023 ASEE Annual Conference & Exposition Proceedings | K86: article | L86: philosophy | M86: moral_status;rights_law | N86: 0 | O86: 10.18260/1-2--43885 | P86: Classify for tracker | Q86: In corpus; not cited by the paper
A87: jaynes2024 | B87: No | C87: No | E87: core | F87: exclusion_bills | G87: Jaynes, T. L. | H87: 2024 | I87: Personhood for artificial intelligence? A cautionary tale from Idaho and Utah | J87: AI & Society (Curmudgeon Corner) | K87: commentary | O87: https://doi.org/10.1007/s00146-024-02006-x | P87: Collect | Q87: Genre note: AI & Society Curmudgeon Corner is an editorially-reviewed opinion column, not a peer-reviewed research section. Kept in Literature (journal-hosted, DOI, referenced) rather than Evidence, unlike mass-media op-eds
A88: corp024 | B88: No | C88: Yes | D88: core | E88: core | F88: corpus_personhood_cluster | G88: Álvaro Falcón Pulido; Deirdre B. Jerry | H88: 2023 | I88: Personhood of Robots | J88: Tax and Robotics | K88: book-chapter | L88: philosophy | M88: moral_status | N88: 0 | O88: 10.1163/9789004538511_004 | P88: Classify for tracker | Q88: In corpus; not cited by the paper
A89: corp041 | B89: No | C89: Yes | D89: core | E89: core | F89: corpus_personhood_cluster | G89: Nassif Bassam | H89: 2020 | I89: PERSONHOOD REVISITED: IMPLICATIONS FOR HUMANOIDS | J89: Studia Universitatis Babeș-Bolyai Theologia Orthodoxa | K89: article | L89: humanities_arts | M89: moral_status;culture_media | N89: 0 | O89: 10.24193/subbto.2020.2.02 | P89: Classify for tracker | Q89: In corpus; not cited by the paper
A90: corp029 | B90: No | C90: Yes | D90: core | E90: core | F90: corpus_personhood_cluster | G90: Janet V. T. Pauketat; Jacy Reese Anthis | H90: 2022 | I90: Predictors of AI Moral Exclusion and Support for AI Rights | J90: TMS Proceedings 2021 | K90: article | L90: psychology | M90: moral_status;rights_law | N90: 0 | O90: 10.1037/tms0000098 | P90: Classify for tracker | Q90: In corpus; not cited by the paper
A91: corp017 | B91: No | C91: Yes | D91: core | E91: core | F91: corpus_personhood_cluster | G91: Daniel Yu | H91: 2024 | I91: Proposing Theological Criteria for Evaluating the Personhood of Artificial Intelligence | J91: Theological Forum | K91: article | L91: humanities_arts | M91: moral_status | N91: 0 | O91: 10.17301/tf.2024.6.116.49 | P91: Classify for tracker | Q91: In corpus; not cited by the paper
A92: corp051 | B92: No | C92: Yes | D92: core | E92: core | F92: corpus_personhood_cluster | G92: Wolfgang Gessner; Gesine Lenore Schiewer | H92: 2008 | I92: Prospects for subjectivity and personhood in androids | J92: RO-MAN 2008 - The 17th IEEE International Symposium on Robot and Human Interactive Communication | K92: article | L92: philosophy | M92: moral_status;consciousness_theory | N92: 1 | O92: 10.1109/roman.2008.4600727 | P92: Classify for tracker | Q92: In corpus; not cited by the paper
A93: corp052 | B93: No | C93: Yes | D93: core | E93: core | F93: corpus_personhood_cluster | G93: Wolfgang Gessner; Gesine Lenore Schiewer | H93: 2008 | I93: Prospects for Subjectivity and Personhood in Androids. Proceedings of IEEE RO-MAN 2008, From Personal Robots ... towards Robots with Personalities? The 17th International Symposium on Robot and Human Interactive Communication, TUM München | K93: article | L93: philosophy | M93: moral_status;consciousness_theory | N93: 0 | O93: W2796137266 | P93: Classify for tracker | Q93: In corpus; not cited by the paper
A94: corp031 | B94: No | C94: Yes | D94: core | E94: core | F94: corpus_personhood_cluster | G94: Eric Martínez; Christoph Winter | H94: 2021 | I94: Protecting Sentient AI: A Survey of Lay Intuitions on Standing, Personhood, and General Legal Protection of Sentient Artificial Intelligence | J94: SSRN Electronic Journal | K94: article | L94: psychology | M94: rights_law;public_perception | N94: 0 | O94: 10.2139/ssrn.3936654 | P94: Classify for tracker | Q94: In corpus; not cited by the paper
A95: corp032 | B95: No | C95: Yes | D95: core | E95: core | F95: corpus_personhood_cluster | G95: Eric Martínez; Christoph Winter | H95: 2021 | I95: Protecting Sentient Artificial Intelligence: A Survey of Lay Intuitions on Standing, Personhood, and General Legal Protection | J95: Frontiers in Robotics and AI | K95: article | L95: psychology | M95: rights_law;public_perception | N95: 24 | O95: 10.3389/frobt.2021.788355 | P95: Classify for tracker | Q95: In corpus; not cited by the paper
A96: corp002 | B96: No | C96: Yes | D96: core | E96: core | F96: corpus_personhood_cluster | G96: Bryson, Jonathan | H96: 2026 | I96: Recognition Ethics (RE): A Unified Codex for Substrate-Agnostic Personhood | K96: article | L96: philosophy | M96: rights_law;moral_status | P96: Classify for tracker | Q96: In corpus; not cited by the paper
A97: corp042 | B97: No | C97: Yes | D97: core | E97: core | F97: corpus_personhood_cluster | G97: David J. Gunkel | H97: 2020 | I97: Should Robots Have Standing? The Moral and Legal Status of Social Robots | J97: Frontiers in Artificial Intelligence and Applications | K97: book-chapter | L97: philosophy | M97: rights_law;moral_status | N97: 1 | O97: 10.3233/faia200956 | P97: Classify for tracker | Q97: In corpus; not cited by the paper
A98: corp003 | B98: No | C98: Yes | D98: core | E98: core | F98: corpus_personhood_cluster | G98: Frank Fagan | H98: 2026 | I98: Stakeholder Personhood and Artificial Intelligence | J98: SSRN Electronic Journal | K98: preprint | L98: law | M98: rights_law | O98: 10.2139/ssrn.6814119 | P98: Classify for tracker | Q98: In corpus; not cited by the paper
A99: corp025 | B99: No | C99: Yes | D99: core | E99: core | F99: corpus_personhood_cluster | G99: Jennifer Blumenthal‐Barby | H99: 2023 | I99: The End of Personhood | J99: The American Journal of Bioethics | K99: article | L99: philosophy | M99: moral_status;rights_law | N99: 50 | O99: 10.1080/15265161.2022.2160515 | P99: Classify for tracker | Q99: In corpus; not cited by the paper
A100: corp026 | B100: No | C100: Yes | D100: core | E100: core | F100: corpus_personhood_cluster | H100: 2023 | I100: The full rights dilemma for AI systems of debatable moral personhood | L100: philosophy | M100: moral_status;rights_law | P100: Classify for tracker | Q100: In corpus; not cited by the paper
...

Sheet Evidence
A1: ref_key | B1: authors_or_source | C1: year | D1: title | E1: outlet | F1: evidence_type | G1: jurisdiction | H1: related_bill | I1: url
A2: abdurasulov2025 | B2: Abdurasulov, A. | C2: 2025 | D2: The new AI arms race changing the war in Ukraine | E2: BBC News | F2: news | I2: https://www.bbc.co.uk/news/articles/cly7jrez2jno
A3: alexander_simon2025 | B3: Alexander, H.; Simon, J. | C3: 2025 | D3: Ohio's AI Personhood Ban Risks Outlawing the Future | E3: Ohio Capital Journal | F3: op_ed | G3: OH | H3: HB 469 | I3: https://ohiocapitaljournal.com/2025/11/25/ohios-ai-personhood-ban-risks-outlawing-the-future/
A4: allianceai_a | B4: Alliance for Secure AI Action | C4: n.d. | D4: The Alliance for Secure AI Action | E4: Organisation site | F4: advocacy | I4: https://secureainow.org/
A5: allianceai_b | B5: Alliance for Secure AI Action | C5: n.d. | D5: The Alliance for Secure AI Staff | E5: Organisation site | F5: advocacy | I5: https://secureainow.org/staff/
A6: amipodcast2025 | B6: Am I? Podcast | C6: 2025 | D6: Lawmaker Explains Why He Wants to Outlaw AI Consciousness | E6: Podcast | F6: media | G6: OH | H6: HB 469 | I6: https://podcasts.apple.com/us/podcast/am-i-id1834212843?i=1000740865127
A7: aquinas | B7: Aquinas, T. | C7: ca. 1270 | D7: Summa Theologiae, Prima Pars, Question 93 | E7: - | F7: primary_religious
A8: ball2025a | B8: Ball, D. | C8: 2025 | D8: Tweet reply on TN SB 1493 and the First Amendment | E8: X (Twitter) | F8: social | G8: TN | H8: HB 1455 / SB 1493 | I8: https://x.com/deanwball/status/2004678006561013931
A9: ball2025b | B9: Ball, D. | C9: 2025 | D9: Tweet commenting on TN SB 1493 | E9: X (Twitter) | F9: social | G9: TN | H9: HB 1455 / SB 1493 | I9: https://x.com/deanwball/status/2004637387402416246
A10: ball_bio | B10: Ball, D. | C10: n.d. | D10: Dean W. Ball - Biography | E10: Personal site | F10: bio | I10: https://www.deanball.com/
A11: banutah_complaint | B11: Ban v. Utah complaint | C11: 2025 | D11: No. 250900869 (Utah Dist. Ct.) | E11: Court filing | F11: legal_doc | G11: UT | H11: HB 249 | I11: https://www.nonhumanrights.org/wp-content/uploads/2025/01/UT-Complaint.pdf
A12: banutah_dismissal | B12: Ban v. Utah dismissal order | C12: 2025 | D12: Memorandum decision and order granting motion to dismiss | E12: Court order | F12: legal_doc | G12: UT | H12: HB 249
A13: barker2026 | B13: Barker, D. | C13: 2026 | D13: Testimony on AB 959 before the Wisconsin Assembly Cttee on Science, Technology and AI | E13: Wisconsin Legislature | F13: testimony | G13: WI | H13: AB 959 / SB 932 | I13: https://docs.legis.wisconsin.gov/misc/lc/hearing_testimony_and_materials/2025/ab959/ab0959_2026_02_04.pdf
A14: berg2025 | B14: Berg, C.; Rosenblatt, J. | C14: 2025 | D14: If AI Becomes Conscious, We Need to Know | E14: Wall Street Journal | F14: op_ed | I14: https://www.wsj.com/opinion/if-ai-becomes-conscious-we-need-to-know-83aa61d8
A15: berry2026 | B15: Berry, S. | C15: 2026 | D15: Testimony on Missouri HB 1746 | E15: Missouri House of Representatives | F15: testimony | G15: MO | H15: HB 1746 | I15: https://documents.house.mo.gov/billtracking/bills261/witnesses/HB1746Testimony2-2.pdf
A16: bible | B16: Bible | C16: - | D16: Genesis 1:26-27 | E16: - | F16: primary_religious
A17: blacks2001 | B17: Black's Law Dictionary | C17: 2001 | D17: 2nd pocket edn (Bryan A. Garner, ed.) | E17: West Group | F17: reference_work
A18: boone2022 | B18: Boone, R. | C18: 2022 | D18: Bill Would Bar Idaho's Lands and Animals From 'Personhood' | E18: Associated Press | F18: news | G18: ID | H18: HB 720 | I18: https://apnews.com/article/united-states-environment-animals-idaho-402c779428a74a6ec9e7994ee977005c
A19: brill2026 | B19: Brill, L. | C19: 2026 | D19: Testimony on AB 959 before the Wisconsin Assembly Committee | E19: Wisconsin Legislature | F19: testimony | G19: WI | H19: AB 959 / SB 932 | I19: https://docs.legis.wisconsin.gov/misc/lc/hearing_testimony_and_materials/2025/ab959/ab0959_2026_02_04.pdf
A20: claggett2025 | B20: Claggett, T. | C20: 2025 | D20: Sponsor testimony on HB 469, Ohio House Technology and Innovation Cttee | E20: Ohio House of Representatives | F20: testimony | G20: OH | H20: HB 469 | I20: https://ohiohouse.gov/committees/technology-and-innovation/bills/hb469
A21: maynard_nd | B21: Cody Maynard for Oklahoma | C21: n.d. | D21: Endorsements | E21: Campaign site | F21: advocacy | G21: OK | H21: HB 3546 | I21: https://codymaynard.com/home/endorsements/
A22: colbert2025 | B22: Colbert, S. | C22: 2025 | D22: The A.I. Stock Bubble | ChatGPT, Grok, Go Erotic | Banning Human-Chatbot Marriage | E22: YouTube | F22: media | I22: https://www.youtube.com/watch?v=o-u_ZkGBcNc
A23: copp2026 | B23: Copp, T. et al. | C23: 2026 | D23: Anthropic's AI tool Claude central to U.S. campaign in Iran, amid a bitter feud | E23: Washington Post | F23: news | I23: https://www.washingtonpost.com/technology/2026/03/04/anthropic-ai-iran-campaign/
A24: cornell_lii | B24: Cornell Legal Information Institute | C24: n.d. | D24: Wex Legal Definitions (Natural Person; Artificial Person) | E24: Legal Information Institute | F24: reference_work | I24: https://www.law.cornell.edu/wex/natural_person
A25: dodson2023 | B25: Dodson, C. | C25: 2023 | D25: Oral testimony on HB 1361 before the North Dakota Legislative Assembly | E25: North Dakota Legislative Assembly | F25: testimony | G25: ND | H25: HB 1361 | I25: https://video.ndlegis.gov/en/PowerBrowser/PowerBrowserV2/20230306/-1/29325
A26: douthat2026 | B26: Douthat, R.; Alvarez Boyd, S. | C26: 2026 | D26: Anthropic's Chief on A.I.: We Don't Know if the Models Are Conscious | E26: New York Times | F26: news | I26: https://www.nytimes.com/2026/02/12/opinion/artificial-intelligence-anthropic-amodei.html
A27: earthlaw2024 | B27: Earth Law Center | C27: 2024 | D27: Utah Advances Anti-Rights of Nature Bill with Implications for AI | E27: Earth Law Center | F27: advocacy | G27: UT | H27: HB 249 | I27: https://www.earthlawcenter.org/blog-entries/2024/2/utah-advances-anti-rights-of-nature-bill-with-implications-for-ai
A28: edmonson2025 | B28: Edmonson, D. | C28: 2025 | D28: RE: HB 469, concerns (testimony to Ohio House Cttee on Technology and Innovation) | E28: Ohio House of Representatives | F28: testimony | G28: OH | H28: HB 469 | I28: https://ohiohouse.gov/committees/technology-and-innovation/bills/hb469
A29: evans2025 | B29: Evans, N. | C29: 2025 | D29: What's in Ohio's Proposal Banning AI Personhood | E29: Ohio Capital Journal | F29: news | G29: OH | H29: HB 469 | I29: https://ohiocapitaljournal.com/2025/11/17/whats-in-ohios-proposal-banning-ai-personhood/
A30: fli_a | B30: Future of Life Institute | C30: n.d. | D30: About us | E30: FLI | F30: advocacy | I30: https://futureoflife.org/about-us/
A31: fli_b | B31: Future of Life Institute | C31: n.d. | D31: Home | E31: FLI | F31: advocacy | I31: https://futureoflife.org/
A32: hochul2025 | B32: Governor Kathy Hochul | C32: 2025 | D32: Governor Hochul Signs Legislation to Require AI Frameworks for AI Frontier Models | E32: NY Governor's Office | F32: press_release | G32: NY | I32: https://www.governor.ny.gov/news/governor-hochul-signs-nation-leading-legislation-require-ai-frameworks-ai-frontier-models
A33: guardian2022 | B33: Guardian | C33: 2022 | D33: Happy the elephant is not a person, says court in key US animal rights case | E33: The Guardian | F33: news | I33: https://www.theguardian.com/us-news/2022/jun/14/elephant-person-animal-rights-happy
A34: hardin2026 | B34: Hardin, C. | C34: 2026 | D34: Governor DeSantis Directs Florida State Agencies to Partner with FLI to Shield Families from AI Harm | E34: Future of Life Institute | F34: press_release | G34: FL | I34: https://futureoflife.org/press-release/desantis-directs-florida-agencies-to-partner-with-fli/
A35: mo_hb1746_test | B35: HB 1746 testimony before the Missouri House Emerging Issues Committee | C35: 2026 | D35: Committee testimony record | E35: Missouri House of Representatives | F35: testimony | G35: MO | H35: HB 1746 | I35: https://documents.house.mo.gov/billtracking/bills261/witnesses/HB1746Testimony2-2.pdf
A36: mo_hb1769_test | B36: HB 1769 testimony before the Missouri House Emerging Issues Committee | C36: 2026 | D36: Committee testimony record | E36: Missouri House of Representatives | F36: testimony | G36: MO | H36: HB 1769 | I36: https://documents.house.mo.gov/billtracking/bills261/witnesses/HB1769Testimony2-2.pdf
A37: hill2022 | B37: Hill, M. | C37: 2022 | D37: Court must decide if an elephant is a person | E37: Associated Press via KSL | F37: news | I37: https://www.ksl.com/article/50407168/court-must-decide-if-an-elephant-is-a-person
A38: iff2022 | B38: Idaho Freedom Foundation | C38: 2022 | D38: House Bill 720 - Personhood, animals, objects | E38: Idaho Freedom Foundation | F38: advocacy | G38: ID | H38: HB 720 | I38: https://idahofreedom.org/house-bill-720-personhood-animals-objects/
A39: littleton_nd | B39: Littleton, M. | C39: n.d. | D39: Tennessee House of Representatives member page | E39: Tennessee General Assembly | F39: member_page | G39: TN | H39: HB 1455 | I39: https://wapp.capitol.tn.gov/apps/LegislatorInfo/member?district=h78
A40: maisonnave2023 | B40: Maisonnave et al. | C40: 2023 | D40: Indigenous leader inspires an Amazon city to grant personhood to an endangered river | E40: AP News | F40: news | I40: https://apnews.com/article/brazil-amazon-wari-indigenous-nature-rights-deforestation-68af65663fb7bd1b9d2051ce10c17a46
A41: massey_nd | B41: Massey, B. | C41: n.d. | D41: Tennessee Senate member page | E41: Tennessee General Assembly | F41: member_page | G41: TN | H41: SB 1493 | I41: https://www.capitol.tn.gov/senate/archives/107GA/members/s6.html
A42: mnhrd_nd | B42: Minnesota House Research Department | C42: n.d. | D42: State Constitutional Amendments | E42: Minnesota House Research | F42: gov_reference | G42: MN | H42: SF 4114 | I42: https://www.house.mn.gov/hrd/pubs/ss/ssconamend.pdf
A43: mbca | B43: Model Business Corporation Act | C43: n.d. | D43: Section 3.02 | E43: - | F43: legal_doc | I43: https://www.lexisnexis.com/documents/pdf/20080618091347_large.pdf
A44: nichols2025a | B44: Nichols, T. | C44: 2025 | D44: AI, States' Rights, and My Visit to WallBuilders | E44: Nichols for Idaho (Substack) | F44: blog | G44: ID | H44: HB 720 | I44: https://nicholsforidaho.substack.com/p/ai-states-rights-and-my-visit-to
A45: nichols2025b | B45: Nichols, T. | C45: 2025 | D45: AI, States' Rights, and the Most Basic Property Right: Owning Yourself | E45: Nichols for Idaho (Substack) | F45: blog | G45: ID | H45: HB 720 | I45: https://nicholsforidaho.substack.com/p/ai-states-rights-and-the-most-basic
A46: nhrp2025 | B46: Nonhuman Rights Project | C46: 2025 | D46: NhRP argues Utah court must allow HB 249 lawsuit to proceed | E46: Nonhuman Rights Project | F46: advocacy | G46: UT | H46: HB 249 | I46: https://www.nonhumanrights.org/blog/hb249-lawsuit-nhrp/
A47: ndcan2023 | B47: North Dakota Can | C47: 2023 | D47: HB 1361 - Definition of Personhood | E47: North Dakota Can | F47: advocacy | G47: ND | H47: HB 1361 | I47: https://ndcan.org/house-bill-1361
A48: ndcan_nd | B48: North Dakota Can | C48: n.d. | D48: About | E48: North Dakota Can | F48: advocacy | G48: ND | I48: https://ndcan.org/about
A49: ndfa_nd | B49: North Dakota Family Alliance | C49: n.d. | D49: North Dakota Family Alliance | E49: NDFA | F49: advocacy | G49: ND | H49: HB 1361 | I49: https://www.ndfamilyalliance.org/
A50: ndleg2023 | B50: North Dakota Legislative Assembly | C50: 2023 | D50: Testimony on and hearing materials on HB 1361 | E50: North Dakota Legislative Assembly | F50: testimony | G50: ND | H50: HB 1361 | I50: https://ndlegis.gov/sites/default/files/resource/68-2023/library/hb1361.pdf
A51: ndleg2025 | B51: North Dakota Legislative Assembly | C51: 2025 | D51: North Dakota HB 1145 Bill Text | E51: North Dakota Legislative Assembly | F51: legal_doc | G51: ND | H51: HB 1145 | I51: https://ndlegis.gov/sites/default/files/resource/69-2025/library/hb1145.pdf
A52: ohiohouse_nd | B52: Ohio House of Representatives | C52: n.d. | D52: HB 469, 135th General Assembly | E52: Ohio House Technology and Innovation Cttee | F52: gov_reference | G52: OH | H52: HB 469 | I52: https://ohiohouse.gov/committees/technology-and-innovation/bills/hb469
A53: perrigo2025 | B53: Perrigo, B.; Chow, A. | C53: 2025 | D53: Senators Reject 10-Year Ban on State-Level AI Regulation | E53: Time | F53: news | I53: https://time.com/7299044/senators-reject-10-year-ban-on-state-level-ai-regulation-in-blow-to-big-tech/
A54: peta2024 | B54: PETA | C54: 2024 | D54: 'Tilikum v. SeaWorld' Case Summary | E54: PETA | F54: advocacy | I54: https://www.peta.org/features/peta-foundation-legal/case-summaries/tilikum-v-seaworld/
A55: pwh_nd | B55: Protect What's Human | C55: n.d. | D55: Protect What's Human | E55: Organisation site | F55: advocacy | I55: https://protectwhatshuman.org/
A56: roche2024 | B56: Roche, L. R. | C56: 2024 | D56: No 'legal personhood' for the Great Salt Lake, Utah legislative committee decides | E56: Deseret News | F56: news | G56: UT | H56: HB 249 | I56: https://www.deseret.com/utah/2024/1/23/24048098/great-salt-lake-legal-personhood-utah-legislature/
A57: romero2024 | B57: Romero, M. | C57: 2024 | D57: Denying Great Salt Lake 'personhood' closes an option for saving the lake, Utahns say | E57: Utah News Dispatch | F57: news | G57: UT | H57: HB 249 | I57: https://utahnewsdispatch.com/2024/01/23/great-salt-lake-personhood-bill/
A58: roy2017 | B58: Roy, E. A. | C58: 2017 | D58: New Zealand river granted same legal rights as human being | E58: The Guardian | F58: news | I58: https://www.theguardian.com/world/2017/mar/16/new-zealand-river-granted-same-legal-rights-as-human-being
A59: sogsl_nd | B59: Save Our Great Salt Lake | C59: n.d. | D59: HOME | E59: Organisation site | F59: advocacy | G59: UT | H59: HB 249 | I59: https://www.saveourgreatsaltlake.org/
A60: tn_sa0922 | B60: SB 837 amendment no. 1 (SA0922) | C60: 2026 | D60: 114th Gen. Assemb., 1st Reg. Sess. (Tenn.) | E60: Tennessee General Assembly | F60: legal_doc | G60: TN | H60: HB 849 / SB 837 | I60: https://www.capitol.tn.gov/Bills/114/Amend/SA0922.pdf
A61: scott2025 | B61: Scott, C. | C61: 2025 | D61: Testimony on Ohio HB 469 | E61: Ohio House of Representatives | F61: testimony | G61: OH | H61: HB 469 | I61: https://ohiohouse.gov/committees/technology-and-innovation/bills/hb469
A62: saet_nd | B62: Society for Ancient and Evangelical Theology | C62: n.d. | D62: Image of God (Imago Dei) | E62: SAET | F62: primary_religious | I62: https://www.saet.ac.uk/Christianity/ImageofGod
A63: steinhauser_bio | B63: Steinhauser, B. | C63: n.d. | D63: Brendan Steinhauser - Public Affairs and Communications Strategist | E63: LinkedIn | F63: bio | I63: https://www.linkedin.com/in/brendanstteinhauser/details/experience/
A64: steinhauser2025 | B64: Steinhauser, B. | C64: 2025 | D64: Protecting Human Agency: HB 469 Testimony | E64: Alliance for Secure AI Action | F64: testimony | G64: OH | H64: HB 469 | I64: https://secureainow.org/ohiohb469/
A65: tan2025 | B65: Tan, G. | C65: 2025 | D65: Tweet: TN SB 1493 is a case study in the idiocy that will destroy AI innovation in America | E65: X (Twitter) | F65: social | G65: TN | H65: HB 1455 / SB 1493 | I65: https://x.com/garrytan/status/2005002574697824594
A66: technet_nd | B66: TechNet | C66: n.d. | D66: TechNet - The Voice of American Innovation | E66: TechNet | F66: advocacy | I66: https://www.technet.org/
A67: tn_ha1260 | B67: Tennessee Amendment No. 4 to HB 1455 / SB 1493 (HA1260) | C67: 2026 | D67: 114th Gen. Assemb., 1st Reg. Sess. | E67: Tennessee General Assembly | F67: legal_doc | G67: TN | H67: HB 1455 / SB 1493 | I67: https://capitol.tn.gov/Bills/114/Amend/HA1260.pdf
A68: tnga_nd | B68: Tennessee General Assembly | C68: n.d. | D68: Tennessee Code Annotated Section 40-35-111 | E68: Tennessee General Assembly | F68: legal_doc | G68: TN | H68: HB 1455 | I68: https://law.justia.com/codes/tennessee/title-40/chapter-35/part-1/section-40-35-111/
A69: prohuman2026 | B69: The Pro-Human AI Declaration | C69: 2026 | D69: The Pro-Human AI Declaration | E69: humanstatement.org | F69: advocacy | I69: https://humanstatement.org
A70: whitehouse2025 | B70: The White House | C70: 2025 | D70: White House Unveils America's AI Action Plan | E70: The White House | F70: press_release | I70: https://www.whitehouse.gov/articles/2025/07/white-house-unveils-americas-ai-action-plan/
A71: ut_house2024 | B71: Utah House Hearing | C71: 2024 | D71: Utah HB 249 House Hearing | E71: Utah State Legislature | F71: testimony | G71: UT | H71: HB 249 | I71: https://le.utah.gov/av/committeeArchive.jsp?timelineID=241561
A72: ut_senate2024 | B72: Utah Senate Hearing | C72: 2024 | D72: Utah Senate Judiciary Committee - HB 249 Hearing | E72: Utah State Legislature | F72: testimony | G72: UT | H72: HB 249 | I72: https://le.utah.gov/av/committeeArchive.jsp?timelineID=246931
A73: wallbuilders2024 | B73: WallBuilders | C73: 2024 | D73: WallBuilders 2024 Impact Report | E73: WallBuilders | F73: advocacy | I73: https://wallbuilders.com/wp-content/uploads/2024/12/2024-WallBuilders-Impact-Report.pdf
A74: wallbuilders2025 | B74: WallBuilders | C74: 2025 | D74: WallBuilders 2025 Impact Report | E74: WallBuilders | F74: advocacy | I74: https://wallbuilders.com/wp-content/uploads/2025/12/2025-WallBuilders-Impact-Report.pdf
A75: wallbuilders_nd | B75: WallBuilders | C75: n.d. | D75: Preserve America's Heritage: Education, Resources and Events | E75: WallBuilders | F75: advocacy | I75: https://wallbuilders.com/
A76: weller2017 | B76: Weller, C. | C76: 2017 | D76: A robot has just been granted citizenship of Saudi Arabia | E76: World Economic Forum | F76: news | I76: https://www.weforum.org/stories/2017/10/a-robot-has-just-been-granted-citizenship-of-saudi-arabia/
A77: weyand2025 | B77: Weyand, Z. | C77: 2025 | D77: Ohio House Bill Introduced to Prohibit Personhood of AI | E77: The Post (Ohio University) | F77: news | G77: OH | H77: HB 469 | I77: https://www.thepostathens.com/article/2025/11/ohio-house-bill-469-prohibit-ai-personhood
A78: williams2024 | B78: Williams, C. | C78: 2024 | D78: What is a person? Here's why Utah is considering a new bill to define it | E78: KSL News | F78: news | G78: UT | H78: HB 249 | I78: https://www.ksl.com/article/50853851/what-is-a-person-heres-why-utah-is-considering-a-new-bill-to-define-it
A79: wiseye2026 | B79: WisconsinEye | C79: 2026 | D79: Assembly Committee on Science, Technology, and AI | E79: WisconsinEye | F79: testimony | G79: WI | H79: AB 959 / SB 932 | I79: https://wiseye.org/2026/02/04/assembly-committee-on-science-technology-and-ai-7/
A80: wef2020 | B80: World Economic Forum | C80: 2020 | D80: What if nature became a legal person? | E80: World Economic Forum | F80: advocacy | I80: https://www.weforum.org/stories/2020/05/nature-legal-personhood/
A81: yurok2019 | B81: Yurok Tribe | C81: 2019 | D81: Resolution Establishing the Rights of the Klamath River (Resolution No. 19-40) | E81: Yurok Tribe | F81: legal_doc | I81: https://ecojurisprudence.org/initiatives/resolution-establishing-rights-of-the-klamath-river/

Sheet Cases
A1: case | B1: citation | C1: court | D1: year | E1: relevance_in_paper
A2: Ban v. Utah | B2: No. 250900869 | C2: Utah Dist. Ct. | D2: 2025 | E2: NhRP challenge to HB 249; dismissed 8 May 2025
A3: Bank Markazi v. Peterson | B3: 578 U.S. 212 | C3: U.S. Supreme Court | D3: 2016 | E3: Congress may amend law affecting pending litigation
A4: Citizens United v. FEC | B4: 558 U.S. 310 | C4: U.S. Supreme Court | D4: 2010 | E4: First Amendment protection for corporate political spending
A5: Cleveland Board of Education v. LaFleur | B5: 414 U.S. 632 | C5: U.S. Supreme Court | D5: 1974 | E5: Irrebuttable presumptions and due process
A6: Coates v. Cincinnati | B6: 402 U.S. 611 | C6: U.S. Supreme Court | D6: 1971 | E6: Vagueness: criminalising 'annoying' behaviour
A7: Connally v. General Construction Co. | B7: 269 U.S. 385 | C7: U.S. Supreme Court | D7: 1926 | E7: Vagueness: 'current rate of per diem wages'
A8: Daubert v. Merrell Dow Pharmaceuticals | B8: 509 U.S. 579 | C8: U.S. Supreme Court | D8: 1993 | E8: Admissibility standard for scientific evidence
A9: Epperson v. Arkansas | B9: 393 U.S. 97 | C9: U.S. Supreme Court | D9: 1968 | E9: Establishment Clause; teaching of evolution
A10: FCC v. Beach Communications | B10: 508 U.S. 307 | C10: U.S. Supreme Court | D10: 1993 | E10: Rational basis test
A11: Kennedy v. Bremerton School District | B11: 597 U.S. 507 | C11: U.S. Supreme Court | D11: 2022 | E11: Free Exercise; personal religious observance
A12: Kitzmiller v. Dover Area School District | B12: 400 F. Supp. 2d 707 | C12: M.D. Pa. | D12: 2005 | E12: Establishment Clause; intelligent design
... A16: United States v. Klein | B16: 80 U.S. (13 Wall.) 128 | C16: U.S. Supreme Court | D16: 1871 | E16: Congress may not prescribe a rule of decision

Sheet Summary
A1: Summary
A3: Literature working set (total rows) | B3: =COUNTA(Literature!A2:A111) | C3: Union of paper scholarly refs and corpus personhood cluster
A4: Cited by the paper | B4: =COUNTIF(Literature!B2:B111,"Yes") | C4: in_paper = Yes
A5: Already held in DM corpus | B5: =COUNTIF(Literature!C2:C111,"Yes") | C5: in_corpus = Yes
A6: Needs verification | B6: =COUNTIF(Literature!C2:C111,"Verify") | C6: Possible retitled duplicate
A7: Paper refs already in corpus | B7: =COUNTIFS(Literature!B2:B111,"Yes",Literature!C2:C111,"Yes") | C7: The dedupe saving
A8: Paper refs NOT in corpus (to collect) | B8: =COUNTIFS(Literature!B2:B111,"Yes",Literature!C2:C111,"No") | C8: New acquisitions
A9: Corpus works the paper missed | B9: =COUNTIFS(Literature!B2:B111,"No",Literature!C2:C111,"Yes") | C9: Finding A: corpus as a source
A11: Tier: core | B11: =COUNTIF(Literature!E2:E111,"core")
A12: Tier: marginal | B12: =COUNTIF(Literature!E2:E111,"marginal")
A14: Action: no action - already held | B14: =COUNTIF(Literature!P2:P111,"No action - already held")
A15: Action: verify against corpus record | B15: =COUNTIF(Literature!P2:P111,"Verify against corpus record")
A16: Action: collect | B16: =COUNTIF(Literature!P2:P111,"Collect")
A17: Action: hold (marginal) | B17: =COUNTIF(Literature!P2:P111,"Hold (marginal)")
A18: Action: classify for tracker | B18: =COUNTIF(Literature!P2:P111,"Classify for tracker")
A20: Evidence records (total) | B20: =COUNTA(Evidence!A2:A81) | C20: Source records for the Phase 2 bill registry
A21: Testimony | B21: =COUNTIF(Evidence!F2:F81,"testimony")
A22: News | B22: =COUNTIF(Evidence!F2:F81,"news")
A23: Advocacy | B23: =COUNTIF(Evidence!F2:F81,"advocacy")
A24: Legal documents | B24: =COUNTIF(Evidence!F2:F81,"legal_doc")
A25: Op-eds | B25: =COUNTIF(Evidence!F2:F81,"op_ed")
A26: Social posts | B26: =COUNTIF(Evidence!F2:F81,"social")
A27: Press releases | B27: =COUNTIF(Evidence!F2:F81,"press_release")
A28: Other (media, bio, reference, religious, gov) | B28: =COUNTA(Evidence!A2:A81)-SUM(B19:B25)
A30: Cases in Table of Cases | B30: =COUNTA(Cases!A2:A16)
A32: Total reference-list entries accounted for | B32: =COUNTIFS(Literature!B2:B111,"Yes")+COUNTA(Evidence!A2:A81) | C32: Scholarly + evidence = the paper's reference list
A33: Scholarly share of reference list | B33: =COUNTIFS(Literature!B2:B111,"Yes")/(COUNTIFS(Literature!B2:B111,"Yes")+COUNTA(Evidence!A2:A81)) | C33: Scholarly / (scholarly + evidence)
